autographql/__init__.py
autographql/admin.py
autographql/apps.py
autographql/base_types.py
autographql/constants.py
autographql/converters.py
autographql/fields.py
autographql/managers.py
autographql/models.py
autographql/monkeypatch.py
autographql/mutation.py
autographql/options.py
autographql/query.py
autographql/registry.py
autographql/schema.py
autographql/types.py
autographql/utils.py
autographql/views.py
autographql/__pycache__/__init__.cpython-310.pyc
autographql/__pycache__/admin.cpython-310.pyc
autographql/__pycache__/apps.cpython-310.pyc
autographql/__pycache__/base_types.cpython-310.pyc
autographql/__pycache__/converters.cpython-310.pyc
autographql/__pycache__/fields.cpython-310.pyc
autographql/__pycache__/managers.cpython-310.pyc
autographql/__pycache__/models.cpython-310.pyc
autographql/__pycache__/monkeypatch.cpython-310.pyc
autographql/__pycache__/mutation.cpython-310.pyc
autographql/__pycache__/options.cpython-310.pyc
autographql/__pycache__/query.cpython-310.pyc
autographql/__pycache__/registry.cpython-310.pyc
autographql/__pycache__/schema.cpython-310.pyc
autographql/__pycache__/types.cpython-310.pyc
autographql/__pycache__/utils.cpython-310.pyc
autographql/__pycache__/views.cpython-310.pyc
autographql/auth/__init__.py
autographql/auth/constants.py
autographql/auth/decorators.py
autographql/auth/middleware.py
autographql/auth/query.py
autographql/auth/rules.py
autographql/auth/utils.py
autographql/auth/__pycache__/__init__.cpython-310.pyc
autographql/auth/__pycache__/constants.cpython-310.pyc
autographql/auth/__pycache__/middleware.cpython-310.pyc
autographql/auth/__pycache__/query.cpython-310.pyc
autographql/auth/__pycache__/utils.cpython-310.pyc
autographql/filters/__init__.py
autographql/filters/converters.py
autographql/filters/fields.py
autographql/filters/types.py
autographql/filters/utils.py
autographql/filters/__pycache__/__init__.cpython-310.pyc
autographql/filters/__pycache__/converters.cpython-310.pyc
django_autographql-0.0.3.dist-info/LICENSE
django_autographql-0.0.3.dist-info/METADATA
django_autographql-0.0.3.dist-info/WHEEL
django_autographql-0.0.3.dist-info/top_level.txt
django_autographql-0.0.3.dist-info/RECORD
