Metadata-Version: 2.1
Name: django-autographql
Version: 0.0.3
Summary: A Django app to automatically generate graphql apis from django code.
Home-page: https://github.com/ehsu0407/django-autographql
Author: Eddie Hsu
Author-email: ehsu0407@gmail.com
License: MIT
Platform: UNKNOWN
Classifier: Environment :: Web Environment
Classifier: Framework :: Django
Classifier: Framework :: Django :: 3.2
Classifier: Intended Audience :: Developers
Classifier: License :: OSI Approved :: MIT License
Classifier: Operating System :: OS Independent
Classifier: Programming Language :: Python
Classifier: Programming Language :: Python :: 3
Classifier: Programming Language :: Python :: 3 :: Only
Classifier: Programming Language :: Python :: 3.6
Classifier: Programming Language :: Python :: 3.7
Classifier: Programming Language :: Python :: 3.8
Classifier: Programming Language :: Python :: 3.9
Classifier: Programming Language :: Python :: 3.10
Classifier: Topic :: Internet :: WWW/HTTP
Classifier: Topic :: Internet :: WWW/HTTP :: Dynamic Content
Requires-Python: >=3.6
License-File: LICENSE
Requires-Dist: Django (>=3.2)
Requires-Dist: djangorestframework (>=3.12)
Requires-Dist: graphene (>=3.0)
Requires-Dist: graphene-django (>=3.0.0b)
Requires-Dist: graphene-django-optimizer (>=0.9.1)
Requires-Dist: bridgekeeper (>=0.9)
